eossr/__init__.py
eossr/_version.py
eossr/utils.py
eossr/version.py
eossr/_dev_version/_dev_version.py
eossr/api/__init__.py
eossr/api/ossr.py
eossr/api/tests/test_ossr.py
eossr/api/zenodo/__init__.py
eossr/api/zenodo/http_status.py
eossr/api/zenodo/zenodo.py
eossr/api/zenodo/tests/test_http_status.py
eossr/api/zenodo/tests/test_zenodo.py
eossr/metadata/__init__.py
eossr/metadata/codemeta.py
eossr/metadata/zenodo.py
eossr/metadata/codemeta2zenodo/__init__.py
eossr/metadata/codemeta2zenodo/converters.py
eossr/metadata/codemeta2zenodo/core.py
eossr/metadata/codemeta2zenodo/utils.py
eossr/metadata/codemeta2zenodo/tests/test_codemeta2zenodo.py
eossr/metadata/codemeta2zenodo/tests/test_codemeta2zenodo_utils.py
eossr/metadata/codemeta2zenodo/tests/test_converters.py
eossr/metadata/schema/__init__.py
eossr/metadata/schema/codemeta.json
eossr/metadata/schema/escape_codemeta_crosswalk.csv
eossr/metadata/tests/__init__.py
eossr/metadata/tests/test_codemeta.py
eossr/metadata/tests/test_zenodo_metadata.py
eossr/metadata/tests/samples/codemeta_contributors_sample.json
eossr/metadata/tests/samples/codemeta_not_valid.json
eossr/metadata/tests/samples/codemeta_sample1.json
eossr/metadata/tests/samples/codemeta_test.json
eossr/metadata/tests/samples/codemeta_valid.json
eossr/metadata/tests/samples/zenodo_test.json
eossr/scripts/__init__.py
eossr/scripts/check_connection_zenodo.py
eossr/scripts/eossr_codemeta2zenodo.py
eossr/scripts/eossr_metadata_validator.py
eossr/scripts/eossr_upload_repository.py
eossr/scripts/eossr_zenodo_validator.py
eossr/scripts/update_codemeta_eossr.py
eossr/scripts/zenodo_user_entries_cleanup.py
eossr/scripts/zip_repository.py
eossr/scripts/tests/test_scripts.py
eossr/tests/conftest.py
eossr/tests/test_globals.py
eossr/tests/test_utils.py
eossr-2.1.1.dist-info/licenses/LICENSE
eossr-2.1.1.dist-info/METADATA
eossr-2.1.1.dist-info/WHEEL
eossr-2.1.1.dist-info/entry_points.txt
eossr-2.1.1.dist-info/top_level.txt
eossr-2.1.1.dist-info/RECORD
