Metadata-Version: 2.4
Name: eossr
Version: 2.1.1
Summary: ESCAPE OSSR library
Author: Enrique Garcia
Author-email: Thomas Vuillaume <vuillaume@lapp.in2p3.fr>
License: MIT License
Project-URL: homepage, https://gitlab.com/escape-ossr/eossr
Classifier: Intended Audience :: Developers
Classifier: Intended Audience :: Science/Research
Classifier: License :: OSI Approved :: MIT License
Classifier: Operating System :: OS Independent
Classifier: Programming Language :: Python
Classifier: Programming Language :: Python :: 3
Classifier: Topic :: Software Development :: Libraries
Classifier: Topic :: Scientific/Engineering
Requires-Python: >=3.8
License-File: LICENSE
Requires-Dist: requests<3.0,>=2.25.0
Requires-Dist: markdown<4.0,>=3.3.6
Requires-Dist: pandas
Requires-Dist: remotezip==0.9.3
Requires-Dist: semver<3,>=2
Requires-Dist: jsonschema
Requires-Dist: jsonref
Requires-Dist: setuptools_scm<8.0
Requires-Dist: beautifulsoup4
Provides-Extra: tests
Requires-Dist: pytest; extra == "tests"
Requires-Dist: pytest-cov; extra == "tests"
Requires-Dist: python-dotenv; extra == "tests"
Provides-Extra: lint
Requires-Dist: ruff>=0.1.0; extra == "lint"
Dynamic: license-file
